arista_lab/__init__.py
arista_lab/cli.py
arista_lab/config/__init__.py
arista_lab/config/interfaces.py
arista_lab/config/peering.py
arista_lab/console.py
arista_lab/templates/__init__.py
arista_lab/templates/interfaces/point-to-point.j2
arista_lab/templates/peering/isp.j2
arista_lab/traffic.py
arista_lab-0.3.1.dist-info/METADATA
arista_lab-0.3.1.dist-info/WHEEL
arista_lab-0.3.1.dist-info/entry_points.txt
arista_lab-0.3.1.dist-info/RECORD
