Metadata-Version: 2.4
Name: arista-lab
Version: 0.3.1
Summary: Simple tooling when working with EOS in labs
Author: Matthieu Tâche
Author-email: mtache@arista.com
Requires-Python: ~=3.12.0
Classifier: Programming Language :: Python :: 3
Classifier: Programming Language :: Python :: 3.12
Requires-Dist: PyYAML (>=6,<6.1)
Requires-Dist: click (>=8.1,<9.0)
Requires-Dist: nornir-jinja2 (>=0.2,<1.0)
Requires-Dist: nornir-napalm (>=0.5,<1.0)
Requires-Dist: requests (>=2.32,<3.0)
Requires-Dist: rich (>=13.7,<14.0)
Requires-Dist: snappi (>=1.34.1,<1.35.0)
Requires-Dist: snappi-ixnetwork (>=1.34.0,<1.35.0)
